{
	"info": {
		"_postman_id": "cf6aeff7-3377-420c-a814-f7d4418b5210",
		"name": "store",
		"schema": "https://schema.getpostman.com/json/collection/v2.1.0/collection.json"
	},
	"item": [
		{
			"name": "customer",
			"item": [
				{
					"name": "get all customers",
					"protocolProfileBehavior": {
						"disableBodyPruning": true
					},
					"request": {
						"method": "GET",
						"header": [],
						"body": {
							"mode": "raw",
							"raw": "{\n    \"jwt\":\"eyJhbGciOiJIUzI1NiIsInR5cCI6IkpXVCJ9.eyJmaXJzdF9uYW1lIjoibW9oYW1lZCIsImlkIjoxLCJpYXQiOjE2NTI0NDQzMDR9.fNEdFZdRQTl3UR54Vh69Ru78XuD_VOuOJ3QJbr5vjc8\"\n}",
							"options": {
								"raw": {
									"language": "json"
								}
							}
						},
						"url": {
							"raw": "http://localhost:5000/customers",
							"protocol": "http",
							"host": [
								"localhost"
							],
							"port": "5000",
							"path": [
								"customers"
							]
						}
					},
					"response": []
				},
				{
					"name": "get customer by id",
					"request": {
						"method": "POST",
						"header": [],
						"body": {
							"mode": "raw",
							"raw": "{\n    \"jwt\":\"eyJhbGciOiJIUzI1NiIsInR5cCI6IkpXVCJ9.eyJmaXJzdF9uYW1lIjoibW9oYW1lZCIsImlkIjoxLCJpYXQiOjE2NTI0NDQzMDR9.fNEdFZdRQTl3UR54Vh69Ru78XuD_VOuOJ3QJbr5vjc8\"\n}",
							"options": {
								"raw": {
									"language": "json"
								}
							}
						},
						"url": {
							"raw": "http://localhost:5000/customers/1",
							"protocol": "http",
							"host": [
								"localhost"
							],
							"port": "5000",
							"path": [
								"customers",
								"1"
							]
						}
					},
					"response": []
				},
				{
					"name": "create customer",
					"request": {
						"method": "POST",
						"header": [],
						"body": {
							"mode": "raw",
							"raw": "{\n    \"first_name\":\"hossam\", \n    \"last_name\":\"ahmed\",\n    \"password\":\"1pass2\"\n}",
							"options": {
								"raw": {
									"language": "json"
								}
							}
						},
						"url": {
							"raw": "http://localhost:5000/customers",
							"protocol": "http",
							"host": [
								"localhost"
							],
							"port": "5000",
							"path": [
								"customers"
							]
						}
					},
					"response": []
				},
				{
					"name": "login",
					"request": {
						"method": "POST",
						"header": [],
						"body": {
							"mode": "raw",
							"raw": "{\n    \"first_name\":\"mohamed\",\n    \"password\":\"mohamed12..\"\n}",
							"options": {
								"raw": {
									"language": "json"
								}
							}
						},
						"url": {
							"raw": "http://localhost:5000/login",
							"protocol": "http",
							"host": [
								"localhost"
							],
							"port": "5000",
							"path": [
								"login"
							]
						}
					},
					"response": []
				},
				{
					"name": "test",
					"protocolProfileBehavior": {
						"disableBodyPruning": true
					},
					"request": {
						"method": "GET",
						"header": [],
						"body": {
							"mode": "raw",
							"raw": "{\n    \"jwt\":\"eyJhbGciOiJIUzI1NiIsInR5cCI6IkpXVCJ9.eyJmaXJzdF9uYW1lIjoibW9oYW1lZCIsImlkIjoxLCJpYXQiOjE2NTI0NDQzMDR9.fNEdFZdRQTl3UR54Vh69Ru78XuD_VOuOJ3QJbr5vjc8\"\n}",
							"options": {
								"raw": {
									"language": "json"
								}
							}
						},
						"url": {
							"raw": "http://localhost:5000/",
							"protocol": "http",
							"host": [
								"localhost"
							],
							"port": "5000",
							"path": [
								""
							]
						}
					},
					"response": []
				}
			]
		},
		{
			"name": "product",
			"item": [
				{
					"name": "get all products",
					"request": {
						"method": "GET",
						"header": [],
						"url": {
							"raw": "http://localhost:5000/products",
							"protocol": "http",
							"host": [
								"localhost"
							],
							"port": "5000",
							"path": [
								"products"
							]
						}
					},
					"response": []
				},
				{
					"name": "get product with id",
					"request": {
						"method": "GET",
						"header": [],
						"url": {
							"raw": "http://localhost:5000/products/1",
							"protocol": "http",
							"host": [
								"localhost"
							],
							"port": "5000",
							"path": [
								"products",
								"1"
							]
						}
					},
					"response": []
				},
				{
					"name": "create new product",
					"request": {
						"method": "POST",
						"header": [],
						"body": {
							"mode": "raw",
							"raw": "{\n    \"jwt\":\"eyJhbGciOiJIUzI1NiIsInR5cCI6IkpXVCJ9.eyJmaXJzdF9uYW1lIjoibW9oYW1lZCIsImlkIjoxLCJpYXQiOjE2NTI0NDQzMDR9.fNEdFZdRQTl3UR54Vh69Ru78XuD_VOuOJ3QJbr5vjc8\",\n    \"name\":\"mobile\" , \n    \"price\":1500\n}",
							"options": {
								"raw": {
									"language": "json"
								}
							}
						},
						"url": {
							"raw": "http://localhost:5000/products",
							"protocol": "http",
							"host": [
								"localhost"
							],
							"port": "5000",
							"path": [
								"products"
							]
						}
					},
					"response": []
				}
			]
		},
		{
			"name": "orders",
			"item": [
				{
					"name": "get order by user id",
					"request": {
						"method": "POST",
						"header": [],
						"body": {
							"mode": "raw",
							"raw": "{\n    \"jwt\":\"eyJhbGciOiJIUzI1NiIsInR5cCI6IkpXVCJ9.eyJmaXJzdF9uYW1lIjoibW9oYW1lZCIsImlkIjoxLCJpYXQiOjE2NTI0NDQzMDR9.fNEdFZdRQTl3UR54Vh69Ru78XuD_VOuOJ3QJbr5vjc8\"\n}",
							"options": {
								"raw": {
									"language": "json"
								}
							}
						},
						"url": {
							"raw": "http://localhost:5000/orders/3",
							"protocol": "http",
							"host": [
								"localhost"
							],
							"port": "5000",
							"path": [
								"orders",
								"3"
							]
						}
					},
					"response": []
				},
				{
					"name": "create order",
					"request": {
						"method": "POST",
						"header": [],
						"body": {
							"mode": "raw",
							"raw": "{\n    \"jwt\":\"eyJhbGciOiJIUzI1NiIsInR5cCI6IkpXVCJ9.eyJmaXJzdF9uYW1lIjoibW9oYW1lZCIsImlkIjoxLCJpYXQiOjE2NTI0NDQzMDR9.fNEdFZdRQTl3UR54Vh69Ru78XuD_VOuOJ3QJbr5vjc8\" ,\n    \"customer_id\":3,\n    \"quantity\":3,\n    \"product_id\":2\n}",
							"options": {
								"raw": {
									"language": "json"
								}
							}
						},
						"url": {
							"raw": "http://localhost:5000/orders/",
							"protocol": "http",
							"host": [
								"localhost"
							],
							"port": "5000",
							"path": [
								"orders",
								""
							]
						}
					},
					"response": []
				}
			]
		}
	]
}